odoo/addons/contract_transmit_method/README.rst
odoo/addons/contract_transmit_method/__init__.py
odoo/addons/contract_transmit_method/__manifest__.py
odoo/addons/contract_transmit_method/i18n/contract_transmit_method.pot
odoo/addons/contract_transmit_method/i18n/fr.po
odoo/addons/contract_transmit_method/i18n/it.po
odoo/addons/contract_transmit_method/i18n/pt_BR.po
odoo/addons/contract_transmit_method/models/__init__.py
odoo/addons/contract_transmit_method/models/contract_contract.py
odoo/addons/contract_transmit_method/models/contract_template.py
odoo/addons/contract_transmit_method/readme/CONTRIBUTORS.md
odoo/addons/contract_transmit_method/readme/DESCRIPTION.md
odoo/addons/contract_transmit_method/static/description/icon.png
odoo/addons/contract_transmit_method/static/description/index.html
odoo/addons/contract_transmit_method/tests/__init__.py
odoo/addons/contract_transmit_method/tests/test_contract.py
odoo/addons/contract_transmit_method/views/contract_contract.xml
odoo/addons/contract_transmit_method/views/contract_template.xml
odoo_addon_contract_transmit_method-18.0.1.1.0.6.dist-info/METADATA
odoo_addon_contract_transmit_method-18.0.1.1.0.6.dist-info/WHEEL
odoo_addon_contract_transmit_method-18.0.1.1.0.6.dist-info/top_level.txt
odoo_addon_contract_transmit_method-18.0.1.1.0.6.dist-info/RECORD
